[{"PuzzleId":"MpjdW","FEN":"2r2k1r/1pN2pp1/8/2P5/3n3p/1P5P/5PP1/1R2R1K1 w - - 0 29","Moves":"c7b5 d4b5","Rating":"1018","Themes":"advantage endgame hangingPiece oneMove","GameUrl":"https://lichess.org/QDNQc3cA#57"},{"PuzzleId":"MpkHT","FEN":"8/6pp/p1R2kb1/1p6/8/Pr3N1P/6PK/8 b - - 1 39","Moves":"f6f5 f3d4 f5e4 d4b3","Rating":"1085","Themes":"crushing endgame fork short","GameUrl":"https://lichess.org/kQxTslQn/black#78"},{"PuzzleId":"MpkjA","FEN":"2r4r/5ppp/pRk1pn2/2P5/p2B4/8/4K1PP/3R4 b - - 4 27","Moves":"c6c7 d4e5","Rating":"1073","Themes":"endgame mate mateIn1 oneMove","GameUrl":"https://lichess.org/i8YVhRYn/black#54"},{"PuzzleId":"MplgZ","FEN":"4r2k/p1p2ppp/3b1q2/8/3P4/2PQ1b1P/P4PP1/R1B3K1 w - - 0 19","Moves":"d3f3 e8e1","Rating":"1073","Themes":"endgame mate mateIn1 oneMove","GameUrl":"https://lichess.org/wSbLsqso#37"},{"PuzzleId":"Mplmq","FEN":"5k2/5pp1/2pN3p/4P3/b2r1P2/6P1/7P/5RK1 b - - 0 31","Moves":"f8e7 d6f5 e7f8 f5d4","Rating":"1056","Themes":"crushing endgame fork short","GameUrl":"https://lichess.org/gJthZ8dz/black#62"},{"PuzzleId":"MpoUb","FEN":"1Q4k1/pp4r1/4pq2/3p4/2p5/2P4R/PP3P2/5K2 b - - 3 45","Moves":"f6f8 h3h8 g8h8 b8f8","Rating":"1197","Themes":"advantage attraction deflection endgame short","GameUrl":"https://lichess.org/4ZCiNyML/black#90"},{"PuzzleId":"Mpor0","FEN":"4r1k1/pp3q2/7p/3pN3/3P4/4r1b1/PPQ3P1/R5K1 w - - 0 25","Moves":"e5f7 e3e1 a1e1 e8e1","Rating":"1099","Themes":"endgame mate mateIn2 short","GameUrl":"https://lichess.org/C0RQfQjC#49"},{"PuzzleId":"Mpr8r","FEN":"8/p2r3k/1p1N3p/2p4P/2Pb4/3R4/P4PP1/6K1 w - - 3 39","Moves":"d6f5 d4f2 g1f2 d7d3","Rating":"1098","Themes":"crushing discoveredAttack endgame short","GameUrl":"https://lichess.org/Jzv9cE4c#77"},{"PuzzleId":"MprKw","FEN":"2R1k1r1/5p2/3PqQ2/2p4P/4P3/5pN1/7K/8 b - - 0 42","Moves":"e6c8 f6e7","Rating":"1129","Themes":"endgame master mate mateIn1 oneMove","GameUrl":"https://lichess.org/MulvtTBP/black#84"}]