[{"PuzzleId":"wKOpA","FEN":"r2q1rk1/1p3pnp/2p1b1p1/p3P3/3PNQ2/P2B4/1P2N1PP/5RK1 b - - 2 23","Moves":"e6f5 e4f6 d8f6 e5f6","Rating":"1147","GameUrl":"https://lichess.org/XkHEtBl1/black#46"},{"PuzzleId":"wKblG","FEN":"4r1k1/3nq2p/pp2Nrp1/3R3n/8/7P/PP2QPPB/4R1K1 w - - 1 26","Moves":"e2d2 f6e6 e1e6 e7e6","Rating":"1181","GameUrl":"https://lichess.org/6qgsRYRg#51"},{"PuzzleId":"wKdBq","FEN":"3Q4/1b3pk1/p3q1pp/3n4/1P3p2/5P1P/2B3P1/3R2K1 w - - 1 36","Moves":"c2b3 e6e3 g1h2 e3b3","Rating":"1029","GameUrl":"https://lichess.org/Xrfch6lL#71"},{"PuzzleId":"wKhUe","FEN":"8/1R6/2r1k1p1/6Bp/p1nP4/P1PK2PP/1P6/8 w - - 5 48","Moves":"d3e4 c4d6 e4f4 d6b7","Rating":"1108","GameUrl":"https://lichess.org/UrnTzeJ1#95"},{"PuzzleId":"wKhyV","FEN":"r1bq1rk1/1p3ppp/pbn2n2/8/3pN3/P2QPN2/1PB2PPP/R1B2RK1 b - - 1 14","Moves":"c8f5 e4f6 d8f6 d3f5 f6f5 c2f5","Rating":"1079","GameUrl":"https://lichess.org/g1zB7J0N/black#28"},{"PuzzleId":"wKmiG","FEN":"rnbqkb1r/ppp2ppp/5n2/3P4/4p3/2N5/PP3PPP/R1BQKBNR b KQkq - 2 6","Moves":"f8b4 d1a4 c7c6 a4b4","Rating":"1052","GameUrl":"https://lichess.org/uoFL9ktp/black#12"},{"PuzzleId":"wKnIN","FEN":"r2qk1r1/ppp1n1bp/2n2Q2/3p4/3P4/6B1/PPP2PPP/RN2K1NR w KQq - 1 12","Moves":"f6e6 c6d4 e6h3 d4c2","Rating":"1092","GameUrl":"https://lichess.org/iYDSLfTf#23"},{"PuzzleId":"wKsjP","FEN":"r1bqkb1r/ppppn1pp/5pn1/3Pp1B1/4P3/2N2N2/PPP2PPP/R2QKB1R w KQkq - 0 7","Moves":"f3h4 f6g5","Rating":"1104","GameUrl":"https://lichess.org/9F6I2BqL#13"},{"PuzzleId":"wKtrW","FEN":"1r1k4/R5p1/1p2B1np/1Pb2p2/3pp3/3P4/4KP2/2R5 w - - 0 45","Moves":"a7g7 g6f4 e2d1 f4e6","Rating":"1084","GameUrl":"https://lichess.org/fJjky7Pe#89"}]