[{"PuzzleId":"gQ7T0","FEN":"8/8/3p3p/2pPk3/ppP3PP/4K3/P1P5/8 w - - 0 34","Moves":"g4g5 h6g5 h4g5 e5f5","Rating":"1164","GameUrl":"https://lichess.org/k7xMH5bJ#67"},{"PuzzleId":"gQ7dV","FEN":"8/2p5/p2k2p1/P1p4p/2K1P2P/6P1/8/8 b - - 0 46","Moves":"c7c6 e4e5 d6e6 c4c5 e6e5 c5c6","Rating":"1046","GameUrl":"https://lichess.org/5ata5bIY/black#92"},{"PuzzleId":"gQ8Ca","FEN":"r4rk1/ppp2ppp/2p5/4P3/3P2q1/2PQ1NPn/PP3PKP/2R2R2 w - - 1 17","Moves":"c1e1 h3f4 g2g1 f4d3","Rating":"1006","GameUrl":"https://lichess.org/HQbVYER5#33"},{"PuzzleId":"gQBs1","FEN":"8/8/B7/P1k1P2p/5K2/3p4/8/5b2 w - - 3 53","Moves":"e5e6 d3d2 e6e7 d2d1q","Rating":"1068","GameUrl":"https://lichess.org/slQiD0nN#105"},{"PuzzleId":"gQG22","FEN":"8/pr3p1p/1p1r1pk1/2nP2p1/2P5/6P1/P5BP/4RRK1 b - - 3 31","Moves":"c5d3 g2e4 g6g7 e4d3","Rating":"1190","GameUrl":"https://lichess.org/6SyZ3PB2/black#62"},{"PuzzleId":"gQHck","FEN":"5r2/8/6K1/6R1/5k2/8/8/8 w - - 3 66","Moves":"g6h5 f8h8 h5g6 h8g8 g6f6 g8g5","Rating":"1110","GameUrl":"https://lichess.org/iebhrph0#131"},{"PuzzleId":"gQIEz","FEN":"8/1p3pk1/6p1/1PP4p/5Q1P/4P1P1/r1r2PK1/8 b - - 10 40","Moves":"c2c5 f4d4 g7g8 d4c5","Rating":"1175","GameUrl":"https://lichess.org/atuxfiio/black#80"},{"PuzzleId":"gQKPU","FEN":"r5k1/5pp1/4p2p/3p4/2qP1P1P/1RP5/6P1/3Q2K1 b - - 2 27","Moves":"a8a1 b3b8 g8h7 d1a1","Rating":"1192","GameUrl":"https://lichess.org/zswTCVtb/black#54"},{"PuzzleId":"gQKfF","FEN":"8/pN2k2p/n1p2p2/1p6/3KP3/3P3P/1P4P1/8 b - - 7 32","Moves":"e7e6 b7c5 a6c5 d4c5","Rating":"1167","GameUrl":"https://lichess.org/7LzL39R4/black#64"}]