[{"PuzzleId":"v3HNM","FEN":"2r2knr/4bpR1/p3p2p/1p2n3/3NN3/P3B3/1PP4P/2K3R1 b - - 2 24","Moves":"e5c4 g7g8 h8g8 e3h6","Rating":"1818","Themes":"crushing deflection middlegame short","GameUrl":"https://lichess.org/zqJ5OEzc/black#48"},{"PuzzleId":"v3alU","FEN":"8/7k/8/5qp1/R2p4/4Pr1P/5PQ1/7K w - - 6 38","Moves":"a4a2 f3h3 h1g1 f5b1 g2f1 h3h1 g1h1 b1f1","Rating":"1856","Themes":"attraction crushing deflection endgame exposedKing fork veryLong","GameUrl":"https://lichess.org/zvjpnIWk#75"},{"PuzzleId":"v3fbr","FEN":"3rk3/ppp3p1/6Np/4Q3/8/P7/KPn3P1/2q5 b - - 0 39","Moves":"e8d7 e5d5 d7c8 g6e7 c8b8 d5d8","Rating":"1930","Themes":"deflection endgame long mate mateIn3","GameUrl":"https://lichess.org/aWzcr733/black#78"},{"PuzzleId":"v3nLs","FEN":"8/p3r1k1/4pn1R/6K1/P2P2P1/5P2/7R/6r1 b - - 19 51","Moves":"e7f7 h6g6 g7f8 g6f6 f7f6 g5f6","Rating":"1908","Themes":"crushing deflection endgame long","GameUrl":"https://lichess.org/trH3Hw4Z/black#102"},{"PuzzleId":"v3pnH","FEN":"8/6pp/5p1k/5q2/8/Q6P/K1r5/3Q4 w - - 3 50","Moves":"a2b3 f5h3 b3c2 h3a3","Rating":"1937","Themes":"crushing deflection endgame short skewer","GameUrl":"https://lichess.org/IRIlD6Kw#99"},{"PuzzleId":"v3qnQ","FEN":"1n3rk1/R5b1/2p4p/2Ppp1p1/Q2Pn3/4BPqb/4P1B1/4NRK1 w - - 1 24","Moves":"f3e4 g3e3 g1h2 f8f1 g2f1 h3f1","Rating":"1991","Themes":"advantage deflection hangingPiece kingsideAttack long middlegame xRayAttack","GameUrl":"https://lichess.org/9Kaa3RQO#47"},{"PuzzleId":"v4A17","FEN":"2rr2k1/5pp1/1q3b1p/8/P7/5Q2/PP1RNPPP/1K5R w - - 3 25","Moves":"h1d1 b6b2 d2b2 d8d1 e2c1 c8c1","Rating":"1865","Themes":"deflection long mate mateIn3 middlegame queensideAttack sacrifice","GameUrl":"https://lichess.org/iZk0m5UF#49"},{"PuzzleId":"v4oSX","FEN":"8/6p1/3R3p/4r1k1/6P1/5K2/5P2/8 b - - 0 42","Moves":"e5e8 f3g3 e8f8 f2f4 f8f4 d6d5 g5f6 g3f4","Rating":"1995","Themes":"crushing deflection endgame rookEndgame veryLong","GameUrl":"https://lichess.org/GJhDUFEP/black#84"},{"PuzzleId":"v4x0l","FEN":"6k1/p1p5/1p5r/3p4/3Pqp2/2P2R1p/PP3Q1P/4B1K1 w - - 0 34","Moves":"f3f4 h6g6 g1f1 e4d3 f2e2 g6g1 f1g1 d3e2","Rating":"1824","Themes":"crushing deflection endgame veryLong","GameUrl":"https://lichess.org/474xblT6#67"}]