[{"PuzzleId":"FxCzq","FEN":"r3nr2/1pp3pk/2nbq2p/4pN1P/p3P1Q1/PP6/1BPN1P2/R3K1R1 b Q - 3 21","Moves":"f8f7 g4g6 e6g6 h5g6","Rating":"1684","Themes":"crushing middlegame short","GameUrl":"https://lichess.org/nYoP55P7/black#42"},{"PuzzleId":"FxEOD","FEN":"2Q5/p4Npk/1p2p2p/1P1b4/3P3q/P4PN1/4n1PP/6K1 w - - 1 35","Moves":"g1f2 h4d4 f2e2 d5c4 c8c4 d4c4","Rating":"1644","Themes":"crushing endgame long sacrifice","GameUrl":"https://lichess.org/6iznx5BR#69"},{"PuzzleId":"FxEbV","FEN":"3r2k1/1p4bp/p1q1ppp1/4n3/8/1QP3P1/PP2NP1P/R4RK1 w - - 0 23","Moves":"e2d4 d8d4 c3d4 e5f3 b3f3 c6f3","Rating":"1664","Themes":"crushing kingsideAttack long middlegame sacrifice","GameUrl":"https://lichess.org/FrBLBbz0#45"},{"PuzzleId":"FxEfA","FEN":"r2qkbnr/pp2pppp/2n5/2p1p3/2B3b1/2N2N2/PPPP1PPP/R1BQK2R w KQkq - 0 6","Moves":"f3e5 c6e5 d1g4 e5g4 c4b5 d8d7 b5d7 e8d7","Rating":"1739","Themes":"crushing hangingPiece opening trappedPiece veryLong","GameUrl":"https://lichess.org/9mbhl4Gp#11"},{"PuzzleId":"FxF0i","FEN":"r1bq1rk1/4bpp1/p1n1p2B/2pp3P/1p2P3/1B1P1P2/PPPQNP2/R3K2R b KQ - 0 15","Moves":"g7h6 d2h6 e7g5 h1g1 f7f6 f3f4","Rating":"1782","Themes":"crushing long middlegame pin","GameUrl":"https://lichess.org/uMc3m0Yu/black#30"},{"PuzzleId":"FxFH1","FEN":"2krr3/p4pp1/1p3q1p/5P2/3N4/2p1Q1P1/P1P2KBP/R7 w - - 1 22","Moves":"e3f3 f6d4 f2f1 d4c4","Rating":"1740","Themes":"crushing hangingPiece middlegame short","GameUrl":"https://lichess.org/IJF5QD8t#43"},{"PuzzleId":"FxHji","FEN":"r4rk1/6pp/1QNq1b2/p1npp3/8/6B1/PP3PPP/2RR2K1 b - - 0 22","Moves":"f8b8 b6c5 d6c5 c1c5","Rating":"1723","Themes":"crushing master middlegame short","GameUrl":"https://lichess.org/JemNfQmH/black#44"},{"PuzzleId":"FxHsF","FEN":"r4rk1/1b2qppp/1p2p3/pP2P3/PbB5/4Q3/1B3PPP/R2R2K1 w - - 6 22","Moves":"e3b6 b4c5 b2a3 c5a3 a1a3 e7a3","Rating":"1641","Themes":"crushing long middlegame","GameUrl":"https://lichess.org/OsjWOA0J#43"},{"PuzzleId":"FxKV8","FEN":"4k3/R3b1p1/7p/1b6/3pB3/1r4P1/3B1PK1/8 b - - 10 44","Moves":"b3b2 e4g6 e8f8 a7a8 e7d8 a8d8","Rating":"1695","Themes":"crushing endgame exposedKing long","GameUrl":"https://lichess.org/RoGsnvVo/black#88"}]