[{"PuzzleId":"nATdj","FEN":"5rk1/r7/5p1p/p3b2P/P1PpP3/1R6/2P1B3/5RK1 w - - 1 29","Moves":"e2g4 a7g7 g1f2 g7g4","Rating":"1284","GameUrl":"https://lichess.org/hFU3yAre#57"},{"PuzzleId":"nAVEz","FEN":"b1kr1b1r/2q2p2/pn1p1p2/Np2pP1p/4P3/2N3P1/PPP1Q1BP/1K1RR3 w - - 4 18","Moves":"c3d5 b6d5 e4d5 c7a5","Rating":"1354","GameUrl":"https://lichess.org/u5FzDy2L#35"},{"PuzzleId":"nAVpH","FEN":"rnb1k2r/ppp2ppp/4q3/8/1b1Pp1P1/1Qn1P2P/PP3PB1/R1B1K1NR w KQkq - 0 11","Moves":"b2c3 e6b3 a2b3 b4c3 e1d1 c3a1","Rating":"1289","GameUrl":"https://lichess.org/bpaLwpH2#21"},{"PuzzleId":"nAY7K","FEN":"R3b1k1/1p1q3p/4p1p1/3pPnQ1/7P/8/2P2PK1/8 b - - 0 25","Moves":"d7e7 g5e7 f5e7 a8e8","Rating":"1223","GameUrl":"https://lichess.org/6k59s8lb/black#50"},{"PuzzleId":"nAaHA","FEN":"5r1k/1p3p1p/2p5/3pq1p1/1P2rN2/P5QP/6PK/3R1R2 w - - 2 30","Moves":"f4e2 e4e2 g3e5 e2e5","Rating":"1299","GameUrl":"https://lichess.org/ZQRMM0nz#59"},{"PuzzleId":"nAc02","FEN":"r3kbnr/pp3ppp/b3p3/q2pP3/3P4/P1N2N2/1P3PPP/R1BQK2R w KQkq - 1 11","Moves":"b2b4 f8b4 a3b4 a5a1","Rating":"1230","GameUrl":"https://lichess.org/PGGBC4GJ#21"},{"PuzzleId":"nAcff","FEN":"r1b1kb1r/pp1n1ppp/5n2/q2B2B1/3Q4/8/PPP2PPP/RN2K1NR w KQkq - 1 9","Moves":"g5d2 a5d5 d4d5 f6d5","Rating":"1310","GameUrl":"https://lichess.org/cjGsY8P8#17"},{"PuzzleId":"nAeln","FEN":"4r1k1/1pp1qp1p/2n2p2/p1Pp4/8/PP1Q1N1P/5PP1/3R2K1 w - - 3 27","Moves":"d3d5 e8d8 d5d8 c6d8","Rating":"1235","GameUrl":"https://lichess.org/MQaoHiNs#53"},{"PuzzleId":"nAhaW","FEN":"N6r/p3k1p1/2BbPp2/3P4/nPPK3p/8/P7/R7 w - - 1 28","Moves":"c6a4 d6e5 d4c5 e5a1 d5d6 e7e6","Rating":"1292","GameUrl":"https://lichess.org/GnNYjMR9#55"}]