[{"PuzzleId":"m8kzM","FEN":"1Q6/2pkn2p/p1p3r1/8/3P1p2/7b/PP1q1PPP/2R1R1K1 w - - 2 26","Moves":"g2g3 f4g3 e1e7 d7e7","Rating":"1490","GameUrl":"https://lichess.org/XF7IUhCX#51"},{"PuzzleId":"m8mUh","FEN":"r2q1rk1/2pb1ppp/p3pn2/1p1n4/1P6/P2Q1N1P/1BB2PP1/R4RK1 b - - 0 17","Moves":"d5f4 b2f6 f4d3 f6d8 f8d8 c2d3","Rating":"1523","GameUrl":"https://lichess.org/UwD4RjfA/black#34"},{"PuzzleId":"m8nRO","FEN":"r4b1r/N1pk1p2/4pnq1/1P1b2pp/2B5/P3BPP1/3Q3P/2KR3R w - - 0 24","Moves":"b5b6 f8a3","Rating":"1472","GameUrl":"https://lichess.org/TbDLzCni#47"},{"PuzzleId":"m8noP","FEN":"4r1k1/1b3pp1/p4b1p/1p4q1/1Pp2N2/P1n1PB1P/1BQ2PP1/3R2K1 w - - 0 27","Moves":"f3b7 c3d1 b2f6 d1e3 c2e4 e8e4","Rating":"1444","GameUrl":"https://lichess.org/iErXsGli#53"},{"PuzzleId":"m8odA","FEN":"2r3k1/p4r1p/4p1p1/5p2/1PpPnP2/q7/2R3PP/2QBR1K1 w - - 1 31","Moves":"c2c4 a3c1 c4c1 c8c1","Rating":"1520","GameUrl":"https://lichess.org/JFtctI6u#61"},{"PuzzleId":"m8pV3","FEN":"3rr2k/pBp2ppp/8/5N2/PB6/5P2/1PKp2P1/R6n b - - 0 26","Moves":"e8e1 a1e1 d2e1q b4e1","Rating":"1590","GameUrl":"https://lichess.org/VZC7a73l/black#52"},{"PuzzleId":"m8sPG","FEN":"7r/1pk5/1n1b4/1p4pr/4B2P/1P4PK/P5R1/2BR4 w - - 0 36","Moves":"e4f3 h5h4 g3h4 h8h4","Rating":"1513","GameUrl":"https://lichess.org/1E5iTvf5#71"},{"PuzzleId":"m8wwu","FEN":"r3k2r/ppp1bppp/2np4/1B2p2b/2P1P1q1/3PBN2/PP1N1P2/R2Q1R1K w kq - 2 13","Moves":"f1g1 g4h3 f3h2 h5d1","Rating":"1507","GameUrl":"https://lichess.org/XRSoAd7c#25"},{"PuzzleId":"m8yJL","FEN":"r5k1/pp2Q1pn/1qp3Np/8/3pP1b1/P7/1PP3PP/5R1K b - - 8 23","Moves":"b6b2 e7f7","Rating":"1582","GameUrl":"https://lichess.org/Tt4GX3u3/black#46"}]