[{"PuzzleId":"RwGpy","FEN":"6k1/7p/5p2/8/4qP2/P5r1/7R/3Q1RK1 w - - 0 32","Moves":"g1f2 e4e3","Rating":"1458","GameUrl":"https://lichess.org/QfabkMPj#63"},{"PuzzleId":"RwIen","FEN":"2k1r3/pppb4/2p3Q1/q5B1/7p/7p/5PP1/3R2K1 b - - 4 30","Moves":"a5a4 g6e8 d7e8 d1d8","Rating":"1563","GameUrl":"https://lichess.org/Luw6Pf93/black#60"},{"PuzzleId":"RwJW1","FEN":"6k1/Qp3p1p/2p2bp1/8/2P2B2/3q1BPb/P4P1P/6K1 w - - 3 25","Moves":"a7e3 d3f1","Rating":"1479","GameUrl":"https://lichess.org/xCM5AU0U#49"},{"PuzzleId":"RwLEZ","FEN":"r6r/ppp1n3/4Pk2/N4b2/3P4/2P2P1p/qP3Q1P/2K1RBR1 w - - 0 25","Moves":"a5c4 a2b1 c1d2 b1c2 d2e3 e7d5","Rating":"1512","GameUrl":"https://lichess.org/gHxNaG3P#49"},{"PuzzleId":"RwLwY","FEN":"1k1r4/p1b3pp/Qp6/2p5/P7/2R1P3/3P2q1/1RK5 w - - 3 36","Moves":"a4a5 g2d2","Rating":"1416","GameUrl":"https://lichess.org/Jp9Gep7D#71"},{"PuzzleId":"RwNqo","FEN":"2kr3r/Bp3ppp/3Ppn2/1B6/P7/1Q3N2/1q3PPP/5RK1 b - - 0 21","Moves":"b2b3 f1c1 b3c2 c1c2","Rating":"1403","GameUrl":"https://lichess.org/084NDMiK/black#42"},{"PuzzleId":"RwPGb","FEN":"1R6/5ppk/2p4p/P1Qb4/6P1/5N1P/4q1PK/3r4 b - - 6 31","Moves":"d5f3 c5f5 g7g6 f5f7","Rating":"1534","GameUrl":"https://lichess.org/2E6oSAgC/black#62"},{"PuzzleId":"RwQx6","FEN":"r1bq1k1R/pp2r1b1/2n1pNQ1/2n1p3/5P2/2N5/PPP3P1/R1B1K3 b Q - 6 20","Moves":"g7h8 g6g8","Rating":"1453","GameUrl":"https://lichess.org/wenbx1u6/black#40"},{"PuzzleId":"RwSzK","FEN":"r5kr/1pp3p1/p1n3B1/3p4/3P4/2P3bp/PP2R3/5RK1 b - - 4 27","Moves":"a8f8 f1f8 g8f8 e2e8","Rating":"1409","GameUrl":"https://lichess.org/QBTMcf9z/black#54"}]