[{"PuzzleId":"nlsnp","FEN":"7k/1p2qB1b/p4R1K/6PQ/P1p5/7P/8/8 w - - 1 61","Moves":"f6e6 e7f8","Rating":"1241","GameUrl":"https://lichess.org/DxoIqyzR#121"},{"PuzzleId":"nltrg","FEN":"5q1k/8/1Q2Rpp1/p6p/2P5/7P/P5PK/5r2 w - - 5 41","Moves":"b6e3 f8b8 e3g3 f1h1 h2h1 b8g3","Rating":"1289","GameUrl":"https://lichess.org/zNepZ1x6#81"},{"PuzzleId":"nlvGf","FEN":"2r1k2r/5pp1/p1NRb3/4P3/2p5/8/PPP4P/2KR4 b k - 4 23","Moves":"h8h2 d6d8 c8d8 d1d8","Rating":"1256","GameUrl":"https://lichess.org/FGf7tE0W/black#46"},{"PuzzleId":"nlwc8","FEN":"4k3/R2b2R1/4p3/5p2/2pPp3/1pP4P/5r2/7K b - - 9 43","Moves":"b3b2 a7a8 d7c8 a8c8","Rating":"1375","GameUrl":"https://lichess.org/YsXEeUbI/black#86"},{"PuzzleId":"nm0V5","FEN":"4r1k1/Q2R1pp1/7p/8/P7/8/1r2qPPP/5RK1 w - - 3 26","Moves":"d7f7 e2f1 g1f1 b2b1","Rating":"1336","GameUrl":"https://lichess.org/AQodMRRq#51"},{"PuzzleId":"nm4FN","FEN":"7k/1Q2p1q1/pp5p/8/8/5p1P/P4P1r/1R5K w - - 4 35","Moves":"h1h2 g7g2","Rating":"1241","GameUrl":"https://lichess.org/kVuoHp5q#69"},{"PuzzleId":"nm58S","FEN":"8/5p2/5P2/5kPB/1p2p2K/3p4/1P6/8 w - - 1 58","Moves":"h5d1 e4e3 h4g3 e3e2 d1e2 d3e2","Rating":"1374","GameUrl":"https://lichess.org/gXrpe0Sa#115"},{"PuzzleId":"nm7Wp","FEN":"2r3k1/p7/6qp/2r2ppR/2P1p1P1/3QP3/5P1P/2R3K1 w - - 0 35","Moves":"d3d4 f5g4 h5h6 g6h6","Rating":"1323","GameUrl":"https://lichess.org/J0O6QQiC#69"},{"PuzzleId":"nm8Ye","FEN":"5Q2/kpp5/1n6/q7/2P1P3/pBP5/P3nP2/1K1R4 w - - 3 34","Moves":"f8b4 e2c3 b1c2 a5b4","Rating":"1316","GameUrl":"https://lichess.org/yr993ufd#67"}]