[{"PuzzleId":"gRPMu","FEN":"3N2k1/R2r2pp/8/1ppp4/1p1n4/8/PP3PPP/4RK2 b - - 0 29","Moves":"d7a7 e1e8","Rating":"884","Themes":"endgame mate mateIn1 oneMove","GameUrl":"https://lichess.org/ERGtdGme/black#58"},{"PuzzleId":"gRUAe","FEN":"1k1r3r/ppp2ppp/3bp3/8/2P1Q3/1P3B1P/P2q1PP1/4R1K1 b - - 2 18","Moves":"f7f5 e4b7","Rating":"584","Themes":"mate mateIn1 middlegame oneMove queensideAttack","GameUrl":"https://lichess.org/dJdrvcn6/black#36"},{"PuzzleId":"gRVyI","FEN":"8/1p6/p1p5/8/1PP5/1P3pk1/6p1/3r1RK1 w - - 3 59","Moves":"f1d1 f3f2","Rating":"594","Themes":"advancedPawn endgame mate mateIn1 oneMove rookEndgame","GameUrl":"https://lichess.org/bL3qJWgq#117"},{"PuzzleId":"gRW3O","FEN":"2k4r/1ppq1N2/1bnp1n2/4p3/P1B1P1b1/1QPP2P1/3N2PK/R4R2 w - - 1 20","Moves":"f7h8 d7h7","Rating":"968","Themes":"mate mateIn1 middlegame oneMove","GameUrl":"https://lichess.org/Sf7hz84p#39"},{"PuzzleId":"gRXc0","FEN":"4k2r/pp2bppp/4p1b1/n2pP3/3P4/P1r1B2P/1P1N1PP1/2KR3R w k - 0 20","Moves":"b2c3 e7a3","Rating":"973","Themes":"bodenMate mate mateIn1 middlegame oneMove queensideAttack","GameUrl":"https://lichess.org/0kVW9NR1#39"},{"PuzzleId":"gRZRP","FEN":"4K3/3P4/4k3/8/8/8/8/7r w - - 6 54","Moves":"d7d8q h1h8","Rating":"861","Themes":"endgame mate mateIn1 oneMove queenRookEndgame","GameUrl":"https://lichess.org/sGEgLdAJ#107"},{"PuzzleId":"gRZhD","FEN":"8/pp6/7q/5R1p/kP4p1/P2P4/1BK5/8 b - - 3 54","Moves":"h6g6 f5a5","Rating":"724","Themes":"endgame mate mateIn1 oneMove","GameUrl":"https://lichess.org/0TDerBAn/black#108"},{"PuzzleId":"gRfQZ","FEN":"kn4R1/3N1p2/4p3/3p4/p2Q4/q7/1r2rP2/1KR5 w - - 0 36","Moves":"d4b2 a3b2","Rating":"684","Themes":"mate mateIn1 middlegame oneMove","GameUrl":"https://lichess.org/d3I7CDNC#71"},{"PuzzleId":"gRgXk","FEN":"6k1/pQ2rppp/4p3/8/3b4/6P1/4PP1P/2R3K1 b - - 0 28","Moves":"e7b7 c1c8","Rating":"600","Themes":"backRankMate endgame mate mateIn1 oneMove","GameUrl":"https://lichess.org/u6kz3xBy/black#56"}]