[{"PuzzleId":"H1ZA1","FEN":"7r/pp1kp3/3pp1p1/2p5/4Pbn1/3P4/PPPBQ1Pq/1K1R1B2 b - - 0 22","Moves":"h2g3 d2e1 g3h2 e2g4","Rating":"2032","Themes":"advantage middlegame short","GameUrl":"https://lichess.org/DtPZZqd5/black#44"},{"PuzzleId":"H1afF","FEN":"r1b5/ppQn3k/3NpqpP/3p4/3P3P/1P6/PP3r2/2KR3R w - - 0 26","Moves":"d6c8 f6f4 c7f4 a8c8 c1b1 f2f4","Rating":"2114","Themes":"advantage deflection intermezzo long middlegame sacrifice","GameUrl":"https://lichess.org/yNP1o15H#51"},{"PuzzleId":"H1b1Z","FEN":"r2q1k2/pp4p1/3p1rB1/2p1pP2/2Pn2Q1/PP1P3P/5PP1/2R2RK1 w - - 2 19","Moves":"g4h4 d4f3 g2f3 f6g6","Rating":"2201","Themes":"crushing middlegame short","GameUrl":"https://lichess.org/6tEBRlrY#37"},{"PuzzleId":"H1bzb","FEN":"1rbqr1k1/ppp1bpp1/5n1p/n7/2B1N3/2NP1Q2/PP1B1PPP/R4RK1 w - - 10 15","Moves":"a1b1 a5c4 d3c4 f6e4 c3e4 f7f5 e4c3 d8d2","Rating":"2215","Themes":"crushing middlegame veryLong","GameUrl":"https://lichess.org/Fyy2CQPF#29"},{"PuzzleId":"H1cwP","FEN":"1k1r3r/1p4b1/2p2p2/2q1p3/2N1P1p1/1QP5/PP4PP/R4R1K w - - 0 25","Moves":"a1d1 d8d1 b3d1 c5c4","Rating":"2252","Themes":"crushing middlegame short","GameUrl":"https://lichess.org/5zVCzSpu#49"},{"PuzzleId":"H1dH0","FEN":"r2r4/pp3pk1/4p1p1/2n3Pp/2pP3n/P5q1/1PPQ2NB/4RR1K b - - 1 28","Moves":"g3h3 g2h4 h3h4 f1f4","Rating":"2390","Themes":"crushing middlegame short","GameUrl":"https://lichess.org/cDFIvJIq/black#56"},{"PuzzleId":"H1eJ4","FEN":"r5k1/ppN3p1/2n2r1p/3pN3/1q1P4/7P/PPP3P1/R2Q2K1 b - - 0 17","Moves":"a8c8 c7d5 b4d4 d1d4 c6d4 d5e7 g8h7 e7c8","Rating":"2327","Themes":"advantage fork middlegame veryLong","GameUrl":"https://lichess.org/I4TOmiYW/black#34"},{"PuzzleId":"H1gFU","FEN":"2r4k/p6p/1bb2p2/4p3/8/3P3K/PPPBQPr1/R4R2 w - - 4 29","Moves":"d2e3 c8g8 f1g1 c6d7 e2g4 g2g4","Rating":"2222","Themes":"crushing exposedKing long middlegame quietMove","GameUrl":"https://lichess.org/pbP9W0Bm#57"},{"PuzzleId":"H1gPv","FEN":"3r4/1q5p/4pkp1/1Pp1Rp2/3n4/r1N3Q1/2P2PPP/3R2K1 w - - 3 28","Moves":"e5c5 d4e2 g1f1 e2g3","Rating":"2232","Themes":"crushing middlegame short","GameUrl":"https://lichess.org/ZmccRBPD#55"}]