[{"PuzzleId":"iYpQi","FEN":"8/R4k2/2p3p1/8/pB6/8/PPb1r1PK/8 b - - 7 35","Moves":"f7e6 a7e7 e6f5 e7e2","Rating":"800","GameUrl":"https://lichess.org/swPnA7gw/black#70"},{"PuzzleId":"iYulG","FEN":"2r3k1/pp4pp/1p2p3/4Pq2/1PP1r3/6P1/4QP1P/2RR2K1 w - - 3 24","Moves":"e2d3 e4e1 d1e1 f5d3","Rating":"965","GameUrl":"https://lichess.org/BQYyjEKI#47"},{"PuzzleId":"iYv3Q","FEN":"1r6/6k1/1p3pp1/2p4p/2NnP3/3PKP2/6PP/2R5 w - - 0 35","Moves":"c1a1 d4c2 e3d2 c2a1","Rating":"767","GameUrl":"https://lichess.org/QtjwDR82#69"},{"PuzzleId":"iYvFX","FEN":"5r2/2p5/pk6/1p3Kp1/2pP1p2/2P2P2/P1P2P2/6R1 w - - 2 31","Moves":"f5g5 f8g8 g5f4 g8g1","Rating":"878","GameUrl":"https://lichess.org/Yy0R7sNk#61"},{"PuzzleId":"iYw4R","FEN":"8/4kppp/4b3/p7/1rP1PpPP/5P2/RP1rBK2/3R4 b - - 3 26","Moves":"b4b2 d1d2 b2d2 a2d2","Rating":"860","GameUrl":"https://lichess.org/VeIpotl9/black#52"},{"PuzzleId":"iYxX4","FEN":"3r2k1/2p2p1p/1bN3p1/1P6/4p3/7P/P1R1K1P1/8 b - - 1 39","Moves":"d8d5 c6e7 g8f8 e7d5","Rating":"675","GameUrl":"https://lichess.org/MdxT3Ufl/black#78"},{"PuzzleId":"iYxcV","FEN":"r6k/pp3prp/3b4/4NpQ1/1P3n2/P7/5PPP/3RR1K1 b - - 0 24","Moves":"g7g5 e5f7 h8g8 f7g5","Rating":"957","GameUrl":"https://lichess.org/mEM2DbbU/black#48"},{"PuzzleId":"iYxit","FEN":"r4rk1/4ppbp/3p2pP/1pnN2P1/1p1pPP2/3B1Q2/qPP4R/2K4R b - - 1 25","Moves":"f8c8 d5e7 g8f8 e7c8","Rating":"894","GameUrl":"https://lichess.org/beAChS5Y/black#50"},{"PuzzleId":"iYyoP","FEN":"2r5/5k1p/2P3p1/R7/8/P4P1P/5KP1/2n5 w - - 0 37","Moves":"a5c5 c1d3 f2e3 d3c5","Rating":"871","GameUrl":"https://lichess.org/iKZKU3wZ#73"}]