[{"PuzzleId":"WB9Pi","FEN":"8/3k4/r2P2p1/P2K2B1/7P/8/8/8 w - - 9 49","Moves":"g5d2 a6d6 d5e5 d6d2","Rating":"999","GameUrl":"https://lichess.org/tWcyZsAj#97"},{"PuzzleId":"WBBee","FEN":"8/7p/2r1k1p1/1R1b1p2/3Bp2P/4P1P1/5P2/6K1 w - - 3 34","Moves":"b5b7 c6c1 g1h2 d5b7","Rating":"924","GameUrl":"https://lichess.org/SUNQDwu8#67"},{"PuzzleId":"WBBvZ","FEN":"8/2N4p/1pK2kp1/8/P6r/1P6/8/8 b - - 1 50","Moves":"h4b4 c7d5 f6g5 d5b4","Rating":"724","GameUrl":"https://lichess.org/llE6dpFS/black#100"},{"PuzzleId":"WBDiS","FEN":"3r1r1k/p2n2pp/b3R3/2pQ2N1/q7/7P/PP3PP1/2R3K1 w - - 3 23","Moves":"e6a6 a4a6 g5f7 f8f7","Rating":"952","GameUrl":"https://lichess.org/jBEjYGsm#45"},{"PuzzleId":"WBF24","FEN":"rn1q1b1r/pppk1p1p/8/4Q1pb/2B2p2/3P3P/PPP3P1/RNB2RK1 w - - 1 12","Moves":"e5h8 f8c5 g1h1 d8h8","Rating":"789","GameUrl":"https://lichess.org/tWC2kyZp#23"},{"PuzzleId":"WBFF4","FEN":"8/8/5pKp/6bP/B5P1/1pk5/5P2/8 w - - 0 52","Moves":"g6f5 b3b2 a4c2 c3c2","Rating":"939","GameUrl":"https://lichess.org/JjO6rMku#103"},{"PuzzleId":"WBFKX","FEN":"8/8/7p/1K4p1/8/1P5P/6k1/8 w - - 0 54","Moves":"b5c5 g2h3 b3b4 g5g4 c5c6 g4g3 b4b5 g3g2","Rating":"922","GameUrl":"https://lichess.org/FCFIfT33#107"},{"PuzzleId":"WBG7j","FEN":"8/7p/4N1p1/5p2/1r2k2P/6P1/5PK1/8 b - - 1 52","Moves":"b4b7 e6c5 e4d5 c5b7","Rating":"722","GameUrl":"https://lichess.org/YitazC0e/black#104"},{"PuzzleId":"WBH3W","FEN":"2r3k1/3R1p2/1pN2p1p/1P6/8/7P/2P2PPK/4r3 b - - 2 33","Moves":"e1c1 c6e7 g8h7 e7c8","Rating":"873","GameUrl":"https://lichess.org/EXGALQEa/black#66"}]