[{"PuzzleId":"GoPyo","FEN":"3r1k1r/1p3p2/pbn2Pp1/2q4p/4QN1B/2P5/PP4PP/5R1K b - - 10 29","Moves":"d8e8 f4g6 f7g6 e4g6 h8g8 g6h6 f8f7 h6h7","Rating":"1847","GameUrl":"https://lichess.org/W65UKyZE/black#58"},{"PuzzleId":"GoTGe","FEN":"1rb2Bk1/p3np1p/3pp1pQ/2p4P/3nP3/2qP2P1/P4PB1/3RK1NR w - - 0 18","Moves":"e1f1 c3d3 d1d3 b8b1 h6c1 b1c1 d3d1 c1d1","Rating":"1890","GameUrl":"https://lichess.org/x0OOC1Ll#35"},{"PuzzleId":"GoZZU","FEN":"2R5/2P5/8/8/2rp1p2/2k2P2/4K3/8 b - - 2 62","Moves":"c3c2 c8d8 c4c7 d8d4 c7e7 d4e4 e7f7 e4c4","Rating":"1970","GameUrl":"https://lichess.org/dYtc4hcP/black#124"},{"PuzzleId":"GoaSs","FEN":"8/3r3p/3P2p1/4kp2/8/4RK2/5PPP/8 b - - 5 35","Moves":"e5d6 e3d3 d6e6 d3d7 e6d7 f3f4 h7h6 f4e5","Rating":"1976","GameUrl":"https://lichess.org/ggVcPGdb/black#70"},{"PuzzleId":"Goojv","FEN":"6k1/5n1p/2p2b2/p2p4/P2Pr3/3QBq2/5P2/1R3K2 b - - 1 29","Moves":"f6d4 b1b8 f7d8 b8d8 g8f7 d8f8 f7f8 e3h6 f8e7 d3f3","Rating":"1896","GameUrl":"https://lichess.org/nkIoTEot/black#58"},{"PuzzleId":"GootQ","FEN":"8/7p/8/1K4n1/P7/8/k7/8 b - - 1 57","Moves":"a2a3 a4a5 g5e6 b5b6 a3b4 a5a6 h7h6 a6a7","Rating":"1871","GameUrl":"https://lichess.org/jDC5M5jE/black#114"},{"PuzzleId":"Gp65l","FEN":"rnb1r1k1/1p3p1p/1pp2qpQ/3p4/3N4/1P1B3P/PBP2PP1/1R4K1 b - - 3 19","Moves":"f6g7 h6g7 g8g7 d4e6 g7g8 e6c7 a8a2 c7e8","Rating":"1971","GameUrl":"https://lichess.org/wlCnPFfi/black#38"},{"PuzzleId":"GpH26","FEN":"r2q2k1/3b2p1/p3p3/1p4P1/2pnN1Q1/P7/1PPB1K2/R7 b - - 0 22","Moves":"d4f5 e4f6 g7f6 g5f6 g8f7 g4h5 f7f6 d2g5","Rating":"1958","GameUrl":"https://lichess.org/GtYLsHEb/black#44"},{"PuzzleId":"GpMpQ","FEN":"3r1rk1/ppp2q1p/6p1/4Q3/8/2B1P3/PP3PPP/R4RK1 w - - 2 21","Moves":"a1d1 f7f2 f1f2 d8d1 c3e1 d1e1 f2f1 f8f1","Rating":"1912","GameUrl":"https://lichess.org/l8P50X0I#41"}]