[{"PuzzleId":"fQWT3","FEN":"2r1r1k1/6p1/4p1Qp/p2q3P/3B4/P1n2NP1/5PK1/4R3 b - - 3 44","Moves":"e8f8 g6g7","Rating":"883","Themes":"mate mateIn1 middlegame oneMove","GameUrl":"https://lichess.org/aQ5R1v6U/black#88"},{"PuzzleId":"fQXLi","FEN":"8/R7/1p4p1/6k1/4Bp2/1P3P1K/P2r3P/6b1 w - - 5 38","Moves":"a7g7 d2h2","Rating":"809","Themes":"endgame mate mateIn1 oneMove","GameUrl":"https://lichess.org/wCyRzM6K#75"},{"PuzzleId":"fQXSQ","FEN":"2r2rk1/1R2ppbp/p1n1N1p1/8/Q7/5N1n/P1PBB1PP/R5qK w - - 5 23","Moves":"a1g1 h3f2","Rating":"966","Themes":"mate mateIn1 middlegame oneMove smotheredMate","GameUrl":"https://lichess.org/ROkeMTFn#45"},{"PuzzleId":"fQYOT","FEN":"2k4r/ppp5/2Q1p3/4Pp2/5P2/5nP1/PPP3Rr/R6K w - - 0 27","Moves":"g2h2 h8h2","Rating":"997","Themes":"arabianMate endgame mate mateIn1 oneMove","GameUrl":"https://lichess.org/EZyFl4xp#53"},{"PuzzleId":"fQa2c","FEN":"r1bqr1k1/pp1n1ppp/5n2/3p4/1b1P4/2NBBN1P/PP3PP1/R2Q1RK1 w - - 4 12","Moves":"c3d5 f6d5","Rating":"902","Themes":"advantage hangingPiece oneMove opening","GameUrl":"https://lichess.org/22RFSOTp#23"},{"PuzzleId":"fQape","FEN":"r3rk2/4Np1B/pnp2p1p/p2b4/3P1q2/2P3R1/PPQ2PPP/4R1K1 b - - 2 27","Moves":"e8e7 g3g8","Rating":"710","Themes":"mate mateIn1 middlegame oneMove","GameUrl":"https://lichess.org/y9uyAast/black#54"},{"PuzzleId":"fQc0t","FEN":"2r5/p5Rp/4kp2/4p3/1R2P2P/3b1P1n/P2N4/4K3 w - - 1 31","Moves":"g7h7 c8c1","Rating":"750","Themes":"endgame master masterVsMaster mate mateIn1 oneMove","GameUrl":"https://lichess.org/CzMaZvs6#61"},{"PuzzleId":"fQcao","FEN":"6k1/1p3ppp/p4b2/2Bqp1P1/3P4/4QP1K/7P/8 b - - 0 39","Moves":"e5d4 e3e8","Rating":"602","Themes":"endgame mate mateIn1 oneMove","GameUrl":"https://lichess.org/iZeOdeYj/black#78"},{"PuzzleId":"fQco5","FEN":"r2q1rk1/1pb2ppp/4b3/1PP1p3/Nn6/3B1N2/5PPP/R2Q1RK1 w - - 0 19","Moves":"d3h7 g8h7","Rating":"637","Themes":"advantage hangingPiece oneMove opening","GameUrl":"https://lichess.org/9a3th2qB#37"}]