[{"PuzzleId":"v9fQ4","FEN":"8/k7/r7/1p6/7P/4PK2/p7/R7 w - - 0 58","Moves":"h4h5 b5b4 f3e2 b4b3","Rating":"1487","GameUrl":"https://lichess.org/YjYdDPaA#115"},{"PuzzleId":"v9fkV","FEN":"2r5/5k1p/1p1n2p1/1Np3P1/P1P5/1P1B3P/5P2/6K1 b - - 1 34","Moves":"d6b7 d3e4 c8b8 e4b7","Rating":"1552","GameUrl":"https://lichess.org/qMWFS6tG/black#68"},{"PuzzleId":"v9iFC","FEN":"6k1/5rpp/3NQ3/p2pP3/5q2/1P6/r4PPP/5RK1 w - - 0 25","Moves":"e6d5 f4f2 f1f2 a2a1 d5d1 a1d1 f2f1 d1f1","Rating":"1540","GameUrl":"https://lichess.org/3m1RiCrI#49"},{"PuzzleId":"v9joB","FEN":"r1bRQ3/1p3pkp/p3p1p1/4q3/8/P4K2/8/R7 b - - 15 38","Moves":"e5a1 e8h8 g7h6 h8a1","Rating":"1573","GameUrl":"https://lichess.org/1bKjwvTn/black#76"},{"PuzzleId":"v9juo","FEN":"4q2k/pp4bp/3Q2p1/8/3P4/1N2r3/PP5P/5RK1 b - - 0 38","Moves":"e8e4 f1f8 g7f8 d6f8","Rating":"1530","GameUrl":"https://lichess.org/Rue9PuR8/black#76"},{"PuzzleId":"v9l9c","FEN":"8/p4pkp/R3p3/4N1p1/1P3n2/P1r2KP1/5P1P/8 w - - 1 38","Moves":"f3e4 f7f5 e4d4 f4e2","Rating":"1568","GameUrl":"https://lichess.org/DYYPkEXa#75"},{"PuzzleId":"v9mB9","FEN":"6k1/R6p/5K2/4n3/1B6/6r1/8/8 b - - 0 44","Moves":"e5g6 a7a8 g6f8 a8f8","Rating":"1590","GameUrl":"https://lichess.org/xQInoHl2/black#88"},{"PuzzleId":"v9mOj","FEN":"2R5/5pk1/2b3p1/P1K3P1/5PP1/8/8/3r4 b - - 2 44","Moves":"d1c1 c5b6 c1b1 b6c6","Rating":"1568","GameUrl":"https://lichess.org/5AXXjx0i/black#88"},{"PuzzleId":"v9oVy","FEN":"2r5/4kpp1/2p1p3/ppq3r1/7Q/P2B4/2P2PPP/1R5K b - - 3 30","Moves":"c8d8 f2f4 d8d4 h4g5 c5g5 f4g5","Rating":"1499","GameUrl":"https://lichess.org/UwsjifzQ/black#60"}]