[{"PuzzleId":"1wjOb","FEN":"2k5/1pp5/8/1R2P2r/5p2/2P5/3K4/8 b - - 0 33","Moves":"c8d7 e5e6 d7e7 b5h5","Rating":"1517","GameUrl":"https://lichess.org/7YBwRER5/black#66"},{"PuzzleId":"1wm9c","FEN":"8/7p/6p1/1p3pP1/PP3P1P/2k1K3/8/8 b - - 0 47","Moves":"c3b4 a4b5 b4b5 e3d4 b5b4 d4e5 b4c5 e5f6","Rating":"1528","GameUrl":"https://lichess.org/dYuZAue1/black#94"},{"PuzzleId":"1wmGg","FEN":"8/8/6p1/6k1/4R3/7P/r3p3/5K2 w - - 0 63","Moves":"e4e2 a2e2 f1e2 g5h4 e2f3 h4h3 f3f4 h3h4","Rating":"1556","GameUrl":"https://lichess.org/wFeTcOjr#125"},{"PuzzleId":"1wnNC","FEN":"1r3R2/2k4p/7p/2ppp3/1rP1b1P1/1NK4P/1P1N4/6R1 w - - 2 35","Moves":"f8b8 d5d4 b3d4 e5d4","Rating":"1465","GameUrl":"https://lichess.org/X8vfoj0v#69"},{"PuzzleId":"1wnXv","FEN":"5R2/8/8/1k3K2/4P2r/5P2/2p5/8 w - - 0 41","Moves":"f8c8 h4h5 f5f4 h5c5 c8c5 b5c5","Rating":"1420","GameUrl":"https://lichess.org/i8pOu5U9#81"},{"PuzzleId":"1woTy","FEN":"8/8/3pB3/3P2p1/2K3P1/8/2k3b1/8 b - - 20 63","Moves":"c2d2 c4b5 d2e3 b5c6","Rating":"1583","GameUrl":"https://lichess.org/bBdY9yWj/black#126"},{"PuzzleId":"1wpJ6","FEN":"R7/5p1k/2N1p1pp/3pP3/8/7P/4qrP1/1Q5K w - - 1 37","Moves":"b1b8 e2f1 h1h2 f1g2","Rating":"1507","GameUrl":"https://lichess.org/YJipNTo8#73"},{"PuzzleId":"1wq7M","FEN":"4r2k/1Q3r1p/8/8/2B2nq1/PP6/5PP1/5RK1 w - - 0 29","Moves":"c4f7 f4e2 g1h1 g4h4","Rating":"1520","GameUrl":"https://lichess.org/FrwSGVcg#57"},{"PuzzleId":"1wqo3","FEN":"2R5/5pkp/6p1/3p2P1/7P/NP1Q1P2/KP6/4r1q1 w - - 19 45","Moves":"d3c3 d5d4 c8g8 g7g8 c3c8 g8g7","Rating":"1401","GameUrl":"https://lichess.org/8JALjkav#89"}]