[{"PuzzleId":"3teGq","FEN":"r4rk1/1b2bppp/1nq1p3/p1p1P1N1/2Pp1P2/1P1Q1N2/PB4PP/R3R1K1 b - - 11 20","Moves":"h7h6 d3h7","Rating":"1010","Themes":"mate mateIn1 middlegame oneMove","GameUrl":"https://lichess.org/bN5avjIz/black#40"},{"PuzzleId":"3tk1V","FEN":"r2q1k1r/pp2pB1p/2np2p1/8/3Nn3/1Q6/PP3PPP/R1B2RK1 b - - 0 13","Moves":"c6d4 c1h6","Rating":"1175","Themes":"mate mateIn1 middlegame oneMove","GameUrl":"https://lichess.org/9LYZWFOt/black#26"},{"PuzzleId":"3toNr","FEN":"8/8/1P4p1/R4p2/P7/6k1/4r1P1/6K1 w - - 0 38","Moves":"b6b7 e2e1","Rating":"1044","Themes":"endgame mate mateIn1 oneMove rookEndgame","GameUrl":"https://lichess.org/33GSUgPQ#75"},{"PuzzleId":"3tyC9","FEN":"2br4/5p1k/2p3pP/1p1nQ3/p4pNq/2P4B/PP3PK1/4R3 b - - 7 38","Moves":"c8g4 e5g7","Rating":"1168","Themes":"master mate mateIn1 middlegame oneMove","GameUrl":"https://lichess.org/CNADs5XM/black#76"},{"PuzzleId":"3u2F5","FEN":"7k/7p/Q2p3q/1p1Pp3/8/2P5/PP3r1P/6RK w - - 0 37","Moves":"a6b5 f2h2","Rating":"1127","Themes":"endgame mate mateIn1 oneMove","GameUrl":"https://lichess.org/WKM0y28Z#73"},{"PuzzleId":"3uF6t","FEN":"6k1/p4pp1/2p3qp/4P2n/6KP/1P2QP2/1P4P1/3N4 w - - 9 33","Moves":"g4h3 g6g3","Rating":"1182","Themes":"endgame mate mateIn1 oneMove","GameUrl":"https://lichess.org/B0hNJK4e#65"},{"PuzzleId":"3uQOv","FEN":"r2q1rk1/3P1pp1/pp5p/3bPQ2/P2p4/2PB4/6PP/2R2RK1 b - - 1 19","Moves":"d5e6 f5h7","Rating":"1044","Themes":"mate mateIn1 middlegame oneMove","GameUrl":"https://lichess.org/DjMqw832/black#38"},{"PuzzleId":"3uSUg","FEN":"4r1k1/2q2pRp/2p1r2b/3pP3/pp3P2/2N5/PPP3QP/1K4R1 b - - 0 23","Moves":"h6g7 g2g7","Rating":"1141","Themes":"kingsideAttack mate mateIn1 middlegame oneMove","GameUrl":"https://lichess.org/X6Ccx552/black#46"},{"PuzzleId":"3uUle","FEN":"r1rb4/2k2p2/p2p2p1/3Pp2p/B2N4/1R3P2/PP5P/1K2R3 b - - 0 31","Moves":"e5d4 e1c1","Rating":"1172","Themes":"endgame master mate mateIn1 oneMove","GameUrl":"https://lichess.org/z6KzYMca/black#62"}]